network_hash_gen/__init__.py
network_hash_gen/base.py
network_hash_gen/cisco_ios/__init__.py
network_hash_gen/cisco_ios/type_5.py
network_hash_gen/cisco_ios/type_9.py
network_hash_gen/juniper_junos/__init__.py
network_hash_gen/juniper_junos/type_1.py
network_hash_gen/juniper_junos/type_6.py
network_hash_gen/juniper_junos/type_9.py
network_hash_gen/utils.py
network_hash_gen-0.3.0.dist-info/LICENSE
network_hash_gen-0.3.0.dist-info/WHEEL
network_hash_gen-0.3.0.dist-info/METADATA
network_hash_gen-0.3.0.dist-info/RECORD
