Metadata-Version: 2.1
Name: network-hash-gen
Version: 0.3.0
Summary: A library to generate hashes for network devices.
Home-page: https://github.com/991jo/network_hash_gen
License: GPL-3.0-or-later
Keywords: password,hash,network,cisco
Author: Johannes Erwerle
Author-email: jo+network_hash_gen@swagspace.org
Requires-Python: >=3.7,<4.0
Classifier: License :: OSI Approved :: GNU General Public License v3 or later (GPLv3+)
Classifier: Programming Language :: Python :: 3
Classifier: Programming Language :: Python :: 3.10
Classifier: Programming Language :: Python :: 3.7
Classifier: Programming Language :: Python :: 3.8
Classifier: Programming Language :: Python :: 3.9
Requires-Dist: passlib (>=1.7.4,<2.0.0)
Requires-Dist: scrypt (>=0.8.20,<0.9.0)
Project-URL: Documentation, https://991jo.github.io/network_hash_gen/
Project-URL: Repository, https://github.com/991jo/network_hash_gen
